model_analyzer/__init__.py
model_analyzer/analyzer.py
model_analyzer/constants.py
model_analyzer/entrypoint.py
model_analyzer/log_formatter.py
model_analyzer/model_analyzer_exceptions.py
model_analyzer/model_manager.py
model_analyzer/cli/__init__.py
model_analyzer/cli/cli.py
model_analyzer/config/__init__.py
model_analyzer/config/generate/__init__.py
model_analyzer/config/generate/automatic_model_config_generator.py
model_analyzer/config/generate/base_model_config_generator.py
model_analyzer/config/generate/brute_plus_binary_parameter_search_run_config_generator.py
model_analyzer/config/generate/brute_run_config_generator.py
model_analyzer/config/generate/concurrency_sweeper.py
model_analyzer/config/generate/config_generator_interface.py
model_analyzer/config/generate/coordinate.py
model_analyzer/config/generate/coordinate_data.py
model_analyzer/config/generate/generator_utils.py
model_analyzer/config/generate/manual_model_config_generator.py
model_analyzer/config/generate/model_config_generator_factory.py
model_analyzer/config/generate/model_profile_spec.py
model_analyzer/config/generate/model_run_config_generator.py
model_analyzer/config/generate/model_variant_name_manager.py
model_analyzer/config/generate/neighborhood.py
model_analyzer/config/generate/optuna_plus_concurrency_sweep_run_config_generator.py
model_analyzer/config/generate/optuna_run_config_generator.py
model_analyzer/config/generate/perf_analyzer_config_generator.py
model_analyzer/config/generate/quick_plus_concurrency_sweep_run_config_generator.py
model_analyzer/config/generate/quick_run_config_generator.py
model_analyzer/config/generate/run_config_generator_factory.py
model_analyzer/config/generate/search_config.py
model_analyzer/config/generate/search_dimension.py
model_analyzer/config/generate/search_dimensions.py
model_analyzer/config/generate/search_parameter.py
model_analyzer/config/generate/search_parameters.py
model_analyzer/config/input/__init__.py
triton_model_analyzer-1.47.0.dist-info/LICENSE
triton_model_analyzer-1.47.0.dist-info/METADATA
triton_model_analyzer-1.47.0.dist-info/WHEEL
triton_model_analyzer-1.47.0.dist-info/dependency_links.txt
triton_model_analyzer-1.47.0.dist-info/entry_points.txt
triton_model_analyzer-1.47.0.dist-info/top_level.txt
triton_model_analyzer-1.47.0.dist-info/RECORD
