Metadata-Version: 2.1
Name: triton-model-analyzer
Version: 1.47.0
Summary: Triton Model Analyzer is a tool to profile and analyze the runtime performance of one or more models on the Triton Inference Server
Home-page: https://developer.nvidia.com/nvidia-triton-inference-server
Author: NVIDIA Inc.
Author-email: sw-dl-triton@nvidia.com
License: BSD
Keywords: triton,tensorrt,inference,server,service,analyzer,nvidia
Classifier: Intended Audience :: Developers
Classifier: Intended Audience :: Science/Research
Classifier: Intended Audience :: Information Technology
Classifier: Topic :: Scientific/Engineering
Classifier: Topic :: Scientific/Engineering :: Image Recognition
Classifier: Topic :: Scientific/Engineering :: Artificial Intelligence
Classifier: Topic :: Software Development :: Libraries
Classifier: Topic :: Utilities
Classifier: License :: OSI Approved :: BSD License
Classifier: Programming Language :: Python :: 3
Classifier: Programming Language :: Python :: 3.8
Classifier: Programming Language :: Python :: 3.9
Classifier: Programming Language :: Python :: 3.10
Classifier: Programming Language :: Python :: 3.11
Classifier: Environment :: Console
Classifier: Natural Language :: English
Classifier: Operating System :: POSIX :: Linux
License-File: LICENSE
Requires-Dist: cryptography>=3.3.2
Requires-Dist: distro>=1.5.0
Requires-Dist: docker>=4.3.1
Requires-Dist: gevent>=22.08.0
Requires-Dist: grpcio<1.68,>=1.41.0
Requires-Dist: httplib2>=0.19.0
Requires-Dist: importlib-metadata>=7.1.0
Requires-Dist: matplotlib>=3.3.4
Requires-Dist: numba>=0.51.2
Requires-Dist: optuna==3.6.1
Requires-Dist: pdfkit>=0.6.1
Requires-Dist: prometheus-client>=0.9.0
Requires-Dist: protobuf
Requires-Dist: psutil>=5.8.0
Requires-Dist: pyyaml>=5.3.1
Requires-Dist: requests>=2.24.0
Requires-Dist: tritonclient[all]>=2.4.0
Requires-Dist: urllib3>=2.0.7
